mig_meow/__init__.py
mig_meow/constants.py
mig_meow/cwl.py
mig_meow/debug.py
mig_meow/fileio.py
mig_meow/info.py
mig_meow/input.py
mig_meow/inputs.py
mig_meow/localrunner.py
mig_meow/logging.py
mig_meow/meow.py
mig_meow/mig.py
mig_meow/monitor_widget.py
mig_meow/notebook.py
mig_meow/pattern.py
mig_meow/recipe.py
mig_meow/report_widget.py
mig_meow/validation.py
mig_meow/version.py
mig_meow/workflow_widget.py
mig_meow/workflows.py
mig_meow/yaml.py
mig_meow/yaml_funcs.py
mig_meow-0.37.dist-info/LICENSE
mig_meow-0.37.dist-info/METADATA
mig_meow-0.37.dist-info/WHEEL
mig_meow-0.37.dist-info/top_level.txt
mig_meow-0.37.dist-info/RECORD
