Metadata-Version: 2.1
Name: mig-meow
Version: 0.37
Summary: MiG based manager for event oriented workflows
Home-page: https://github.com/PatchOfScotland/mig_meow
Author: David Marchant
Author-email: d.marchant@ed-alumni.net
License: UNKNOWN
Platform: UNKNOWN
Classifier: Programming Language :: Python :: 3
Classifier: License :: OSI Approved :: GNU General Public License (GPL)
Classifier: Operating System :: OS Independent
Requires-Dist: graphviz (==0.13.2)
Requires-Dist: bqplot (==0.12.13)
Requires-Dist: IPython (==7.16.1)
Requires-Dist: requests (==2.24.0)
Requires-Dist: ipywidgets (==7.5.1)
Requires-Dist: PyYAML (>=5.4)
Requires-Dist: nbformat (==5.1.2)
Requires-Dist: watchdog
Requires-Dist: notebook-parameterizer
Requires-Dist: papermill
Requires-Dist: ipydatetime
Provides-Extra: test
Requires-Dist: numpy ; extra == 'test'
